LICENSE
MANIFEST.in
README.rst
requirements.txt
setup.cfg
setup.py
modoboa_admin_relaydomains/__init__.py
modoboa_admin_relaydomains/app_settings.py
modoboa_admin_relaydomains/apps.py
modoboa_admin_relaydomains/factories.py
modoboa_admin_relaydomains/forms.py
modoboa_admin_relaydomains/general_callbacks.py
modoboa_admin_relaydomains/handlers.py
modoboa_admin_relaydomains/lib.py
modoboa_admin_relaydomains/models.py
modoboa_admin_relaydomains/modo_extension.py
modoboa_admin_relaydomains/postfix_maps.py
modoboa_admin_relaydomains/tests.py
modoboa_admin_relaydomains/urls.py
modoboa_admin_relaydomains/views.py
modoboa_admin_relaydomains.egg-info/PKG-INFO
modoboa_admin_relaydomains.egg-info/SOURCES.txt
modoboa_admin_relaydomains.egg-info/dependency_links.txt
modoboa_admin_relaydomains.egg-info/not-zip-safe
modoboa_admin_relaydomains.egg-info/requires.txt
modoboa_admin_relaydomains.egg-info/top_level.txt
modoboa_admin_relaydomains/locale/cs_CZ/LC_MESSAGES/django.mo
modoboa_admin_relaydomains/locale/cs_CZ/LC_MESSAGES/django.po
modoboa_admin_relaydomains/locale/cs_CZ/LC_MESSAGES/djangojs.mo
modoboa_admin_relaydomains/locale/cs_CZ/LC_MESSAGES/djangojs.po
modoboa_admin_relaydomains/locale/de/LC_MESSAGES/django.mo
modoboa_admin_relaydomains/locale/de/LC_MESSAGES/django.po
modoboa_admin_relaydomains/locale/de/LC_MESSAGES/djangojs.mo
modoboa_admin_relaydomains/locale/de/LC_MESSAGES/djangojs.po
modoboa_admin_relaydomains/locale/en/LC_MESSAGES/django.mo
modoboa_admin_relaydomains/locale/en/LC_MESSAGES/django.po
modoboa_admin_relaydomains/locale/en/LC_MESSAGES/djangojs.mo
modoboa_admin_relaydomains/locale/en/LC_MESSAGES/djangojs.po
modoboa_admin_relaydomains/locale/es/LC_MESSAGES/django.mo
modoboa_admin_relaydomains/locale/es/LC_MESSAGES/django.po
modoboa_admin_relaydomains/locale/es/LC_MESSAGES/djangojs.mo
modoboa_admin_relaydomains/locale/es/LC_MESSAGES/djangojs.po
modoboa_admin_relaydomains/locale/fr/LC_MESSAGES/django.mo
modoboa_admin_relaydomains/locale/fr/LC_MESSAGES/django.po
modoboa_admin_relaydomains/locale/fr/LC_MESSAGES/djangojs.mo
modoboa_admin_relaydomains/locale/fr/LC_MESSAGES/djangojs.po
modoboa_admin_relaydomains/locale/it/LC_MESSAGES/django.mo
modoboa_admin_relaydomains/locale/it/LC_MESSAGES/django.po
